sokrates_mcp/__init__.py
sokrates_mcp/main.py
sokrates_mcp/mcp_config.py
sokrates_mcp/utils.py
sokrates_mcp/workflow.py
sokrates_mcp-0.4.3.dist-info/licenses/LICENSE
sokrates_mcp_client/__init__.py
sokrates_mcp_client/mcp_client_example.py
sokrates_mcp-0.4.3.dist-info/METADATA
sokrates_mcp-0.4.3.dist-info/WHEEL
sokrates_mcp-0.4.3.dist-info/entry_points.txt
sokrates_mcp-0.4.3.dist-info/top_level.txt
sokrates_mcp-0.4.3.dist-info/RECORD
