Metadata-Version: 2.4
Name: sokrates-mcp
Version: 0.4.3
Summary: A templated MCP server for demonstration and quick start.
Author-email: Julian Weber <julianweberdev@gmail.com>
License: MIT License
Project-URL: Homepage, https://github.com/Kubementat/sokrates-mcp
Project-URL: Repository, https://github.com/Kubementat/sokrates-mcp
Keywords: mcp,llm,tools,system-monitoring,ai,prompt refinement,idea generation
Requires-Python: >=3.10
License-File: LICENSE
Requires-Dist: fastmcp
Requires-Dist: sokrates
Requires-Dist: pydantic
Requires-Dist: PyYAML
Dynamic: license-file
